LICENSE
MANIFEST.in
README.rst
VERSION
setup.py
selenic/__init__.py
selenic/builder.py
selenic/capabilities.py
selenic/config.py
selenic/datatables.py
selenic/outil.py
selenic/tables.py
selenic/util.py
selenic.egg-info/PKG-INFO
selenic.egg-info/SOURCES.txt
selenic.egg-info/dependency_links.txt
selenic.egg-info/pbr.json
selenic.egg-info/top_level.txt
selenic/remote/__init__.py
selenic/remote/base.py
selenic/remote/browserstack.py
selenic/remote/saucelabs.py