Metadata-Version: 1.1
Name: selenic
Version: 0.13.1
Summary: Some selenium infrastructure for testing.
Home-page: https://github.com/mangalam-research/selenic
Author: Louis-Dominique Dubeau
Author-email: ldd@lddubeau.com
License: MPL 2.0
Keywords: selenium,testing
Platform: UNKNOWN
Classifier: Programming Language :: Python :: 3 :: Only
Classifier: Development Status :: 4 - Beta
Classifier: Intended Audience :: Developers
Classifier: License :: OSI Approved :: Mozilla Public License 2.0 (MPL 2.0)
Classifier: Operating System :: POSIX
Classifier: Topic :: Software Development :: Version Control
Classifier: Topic :: Software Development :: Quality Assurance
